torax/__init__.py
torax/conftest.py
torax/run_simulation_main.py
torax/_src/array_typing.py
torax/_src/constants.py
torax/_src/interpolated_param.py
torax/_src/jax_utils.py
torax/_src/math_utils.py
torax/_src/physics_models.py
torax/_src/simulation_app.py
torax/_src/state.py
torax/_src/version.py
torax/_src/xnp.py
torax/_src/config/__init__.py
torax/_src/config/build_runtime_params.py
torax/_src/config/config_loader.py
torax/_src/config/numerics.py
torax/_src/config/runtime_params_slice.py
torax/_src/config/runtime_validation_utils.py
torax/_src/core_profiles/convertors.py
torax/_src/core_profiles/getters.py
torax/_src/core_profiles/initialization.py
torax/_src/core_profiles/profile_conditions.py
torax/_src/core_profiles/updaters.py
torax/_src/core_profiles/plasma_composition/electron_density_ratios.py
torax/_src/core_profiles/plasma_composition/electron_density_ratios_zeff.py
torax/_src/core_profiles/plasma_composition/impurity_fractions.py
torax/_src/core_profiles/plasma_composition/ion_mixture.py
torax/_src/core_profiles/plasma_composition/plasma_composition.py
torax/_src/edge/collisional_radiative_models.py
torax/_src/edge/divertor_sol_1d.py
torax/_src/edge/extended_lengyel.py
torax/_src/edge/extended_lengyel_defaults.py
torax/_src/edge/extended_lengyel_formulas.py
torax/_src/edge/mavrin_2017_charge_states_data.py
torax/_src/edge/mavrin_2017_cooling_rate_data.py
torax/_src/fvm/__init__.py
torax/_src/fvm/block_1d_coeffs.py
torax/_src/fvm/calc_coeffs.py
torax/_src/fvm/cell_variable.py
torax/_src/fvm/convection_terms.py
torax/_src/fvm/diffusion_terms.py
torax/_src/fvm/discrete_system.py
torax/_src/fvm/enums.py
torax/_src/fvm/fvm_conversions.py
torax/_src/fvm/implicit_solve_block.py
torax/_src/fvm/jax_root_finding.py
torax/_src/fvm/newton_raphson_solve_block.py
torax/_src/fvm/optimizer_solve_block.py
torax/_src/fvm/residual_and_loss.py
torax/_src/geometry/__init__.py
torax/_src/geometry/circular_geometry.py
torax/_src/geometry/geometry.py
torax-1.1.1.dist-info/licenses/LICENSE
torax-1.1.1.dist-info/METADATA
torax-1.1.1.dist-info/WHEEL
torax-1.1.1.dist-info/entry_points.txt
torax-1.1.1.dist-info/top_level.txt
torax-1.1.1.dist-info/RECORD
