Metadata-Version: 2.4
Name: torax
Version: 1.1.1
Summary: Differentiable 1D tokamak plasma transport simulator in JAX.
Author-email: TORAX authors <torax-dev@google.com>
License-Expression: Apache-2.0
Project-URL: homepage, https://github.com/google-deepmind/torax
Project-URL: repository, https://github.com/google-deepmind/torax
Project-URL: documentation, https://github.com/google-deepmind/torax/blob/main/README.md
Classifier: Intended Audience :: Science/Research
Requires-Python: >=3.11
License-File: LICENSE
Requires-Dist: absl-py>=2.0.0
Requires-Dist: typing_extensions>=4.2.0
Requires-Dist: immutabledict>=1.0.0
Requires-Dist: jax>=0.7.0
Requires-Dist: jaxlib>=0.7.0
Requires-Dist: jaxopt>=0.8.2
Requires-Dist: flax>=0.10.0
Requires-Dist: fusion_surrogates==0.1.0
Requires-Dist: matplotlib>=3.3.0
Requires-Dist: numpy>2
Requires-Dist: setuptools; python_version >= "3.11"
Requires-Dist: chex>=0.1.88
Requires-Dist: equinox>=0.11.3
Requires-Dist: PyYAML>=6.0.1
Requires-Dist: xarray>=2024.11.0
Requires-Dist: netcdf4>=1.7.2
Requires-Dist: h5netcdf>=1.3.0
Requires-Dist: scipy>=1.13.0
Requires-Dist: jaxtyping>=0.3.2
Requires-Dist: contourpy>=1.2.1
Requires-Dist: eqdsk>=0.4.0
Requires-Dist: pydantic>=2.10.5
Requires-Dist: tqdm>=4.67.0
Requires-Dist: treelib>=1.3.2
Requires-Dist: imas-python>=2.0.1
Requires-Dist: typeguard==2.13.3
Provides-Extra: dev
Requires-Dist: isort; extra == "dev"
Requires-Dist: pytest; extra == "dev"
Requires-Dist: pytest-xdist; extra == "dev"
Requires-Dist: pytest-shard; extra == "dev"
Requires-Dist: pylint>=2.6.0; extra == "dev"
Requires-Dist: pyink; extra == "dev"
Requires-Dist: sphinxcontrib-apidoc; extra == "dev"
Requires-Dist: sphinx-autodoc-typehints; extra == "dev"
Requires-Dist: sphinx-rtd-theme; extra == "dev"
Requires-Dist: sphinx_copybutton; extra == "dev"
Requires-Dist: sphinx_design; extra == "dev"
Requires-Dist: sphinx_remove_toctrees; extra == "dev"
Provides-Extra: tutorial
Requires-Dist: seaborn; extra == "tutorial"
Requires-Dist: notebook; extra == "tutorial"
Dynamic: license-file
